sweetify/__init__.py
sweetify/__version__.py
sweetify/encoder.py
sweetify/sweetify.py
sweetify/templatetags/__init__.py
sweetify/templatetags/sweetify.py
sweetify/views.py
sweetify-2.2.0.dist-info/LICENSE
sweetify-2.2.0.dist-info/WHEEL
sweetify-2.2.0.dist-info/METADATA
sweetify-2.2.0.dist-info/RECORD
