Metadata-Version: 2.1
Name: sweetify
Version: 2.2.0
Summary: SweetAlert integration for Django
Home-page: https://github.com/Atrox/sweetify-django
License: BSD-3-Clause
Keywords: sweetalert,django,messages
Author: Atrox
Author-email: hello@atrox.dev
Requires-Python: >=3.6.2,<4.0.0
Classifier: License :: OSI Approved :: BSD License
Classifier: Programming Language :: Python :: 3
Classifier: Programming Language :: Python :: 3.10
Classifier: Programming Language :: Python :: 3.7
Classifier: Programming Language :: Python :: 3.8
Classifier: Programming Language :: Python :: 3.9
Project-URL: Repository, https://github.com/Atrox/sweetify-django
